README.rst
setup.cfg
setup.py
sascar_client/__init__.py
sascar_client/database.py
sascar_client/soap_client.py
sascar_client.egg-info/PKG-INFO
sascar_client.egg-info/SOURCES.txt
sascar_client.egg-info/dependency_links.txt
sascar_client.egg-info/entry_points.txt
sascar_client.egg-info/not-zip-safe
sascar_client.egg-info/requires.txt
sascar_client.egg-info/top_level.txt
sascar_client/scripts/__init__.py
sascar_client/scripts/cli.py