Metadata-Version: 1.1
Name: sascar-client
Version: 1.2
Summary: A client to sascar soap web service.
Home-page: https://github.com/ibamacsr/sascar_client
Author: Wille Marcel
Author-email: wille@wille.blog.br
License: GPLv3
Platform: UNKNOWN
Classifier: Development Status :: 4 - Beta
Classifier: Environment :: Console
Classifier: License :: OSI Approved :: GNU General Public License v3 (GPLv3)
Classifier: Natural Language :: English
Classifier: Programming Language :: Python :: 2 :: Only
